<?xml version="1.0" encoding="gb2312"?>
<ApproveDataInfo>
	<TableName> sp_shenqin </TableName>
	<Column>
		<ColName>APPROVE_TYPE</ColName>
		<ColValue>1071</ColValue>
	</Column>
	<Column>
		<ColName>APPROVE_ITEM</ColName>
		<ColValue>越秀区自主创业补贴</ColValue>
	</Column>
	<Column>
		<ColName>IS_ENTERPRISE</ColName>
		<ColValue>1</ColValue>
	</Column>
	<Column>
		<ColName>ORIGINAL_SEQ</ColName>
		<ColValue>162878863</ColValue>
	</Column>
	<Column>
		<ColName>CONTROL_SEQ</ColName>
		<ColValue>162878863</ColValue>
	</Column>
	<Column>
		<ColName>APPLY_TYPE</ColName>
		<ColValue>1</ColValue>
	</Column>
	<Column>
		<ColName>CUST_CER_TYPE</ColName>
		<ColValue>null</ColValue>
	</Column>
	<Column>
		<ColName>CUST_CER_ID</ColName>
		<ColValue>330726196507040016</ColValue>
	</Column>
	<Column>
		<ColName>CUST_NAME</ColName>
		<ColValue>莫幼杰</ColValue>
	</Column>
	<Column>
		<ColName>CUST_CONTACT_PERSON</ColName>
		<ColValue>莫幼杰</ColValue>
	</Column>
	<Column>
		<ColName>CUST_CONTACT_WAY</ColName>
		<ColValue/>
	</Column>
	<Column>
		<ColName>CUST_MOBILE</ColName>
		<ColValue>15919306983</ColValue>
	</Column>
	<Column>
		<ColName>CUST_ADDR</ColName>
		<ColValue/>
	</Column>
	<Column>
		<ColName>PROJ_NAME</ColName>
		<ColValue>越秀区自主创业补贴</ColValue>
	</Column>
	<Column>
		<ColName>APPROVE_DEALWITH_WAY</ColName>
		<ColValue>1</ColValue>
	</Column>
	<Column>
		<ColName>START_MAN</ColName>
		<ColValue/>
	</Column>
	<Column>
		<ColName>START_DATE</ColName>
		<ColValue>2015-11-02 00:00:00</ColValue>
	</Column>
	<Column>
		<ColName>RECEIVE_STUFF</ColName>
		<ColValue>1、用工增减员表一式三份；
2、开户许可证或身份证复印件一式两份。
3、营业执照副本一式两份；
		</ColValue>
	</Column>
	<Column>
		<ColName>FINISH_TIMELIMIT</ColName>
		<ColValue>0</ColValue>
	</Column>
	<Column>
		<ColName>FINISH_LEGAL_TIMELIMIT</ColName>
		<ColValue/>
	</Column>
	<Column>
		<ColName>AREA_SEQ</ColName>
		<ColValue>1</ColValue>
	</Column>
	<Column>
		<ColName>COMMON_CODE</ColName>
		<ColValue>162878863</ColValue>
	</Column>
	<Column>
		<ColName>APPLY_WEB</ColName>
		<ColValue>null</ColValue>
	</Column>
	<Column>
		<ColName>PARENT_ITEM</ColName>
		<ColValue>null</ColValue>
	</Column>
	<Column>
		<ColName>PARENT_ITEM_NAME</ColName>
		<ColValue>null</ColValue>
	</Column>
	<Column>
		<ColName>CONTROL_SEQ</ColName>
		<ColValue>162878863</ColValue>
	</Column>
	<Column>
		<ColName>CUST_MAIL</ColName>
		<ColValue>null</ColValue>
	</Column>
	<Column>
		<ColName>OLD_CONTROL_SEQ</ColName>
		<ColValue>162878863</ColValue>
	</Column>
	<Column>
		<ColName>START_MEMO</ColName>
		<ColValue>null</ColValue>
	</Column>
	<Column>
		<ColName>ISP_PLAT_USER</ColName>
		<ColValue>511702197404273798</ColValue>
	</Column>
	<Column>
		<ColName>ISP_PLAT_CODE</ColName>
		<ColValue>02</ColValue>
	</Column>
	<Column>
		<ColName>ISP_PLAT_SRC</ColName>
		<ColValue>5t6y7u8i9o0p1q2w3e4r5t6y7u8i9o</ColValue>
	</Column>
</ApproveDataInfo>
